galaxy/data/__init__.py
galaxy/data/cache.py
galaxy/data/constant.py
galaxy/data/db/__init__.py
galaxy/data/db/dao/__init__.py
galaxy/data/db/dao/company.py
galaxy/data/db/dao/file.py
galaxy/data/db/dao/finance.py
galaxy/data/db/dao/infra.py
galaxy/data/db/dao/institution.py
galaxy/data/db/dao/iso.py
galaxy/data/db/dao/prog.py
galaxy/data/db/dao/time.py
galaxy/data/db/dao/trading.py
galaxy/data/db/db.py
galaxy/data/db/djangodb.py
galaxy/data/db/orm/__init__.py
galaxy/data/db/orm/django/__init__.py
galaxy/data/db/orm/django/company.py
galaxy/data/db/orm/django/file.py
galaxy/data/db/orm/django/finance.py
galaxy/data/db/orm/django/infra.py
galaxy/data/db/orm/django/institution.py
galaxy/data/db/orm/django/iso.py
galaxy/data/db/orm/django/prog.py
galaxy/data/db/orm/django/time.py
galaxy/data/db/orm/django/trading.py
galaxy/data/db/orm/sqlalchemy/__init__.py
galaxy/data/db/orm/sqlalchemy/company.py
galaxy/data/db/orm/sqlalchemy/file.py
galaxy/data/db/orm/sqlalchemy/finance.py
galaxy/data/db/orm/sqlalchemy/infra.py
galaxy/data/db/orm/sqlalchemy/institution.py
galaxy/data/db/orm/sqlalchemy/iso.py
galaxy/data/db/orm/sqlalchemy/prog.py
galaxy/data/db/orm/sqlalchemy/time.py
galaxy/data/db/orm/sqlalchemy/trading.py
galaxy/data/model/__init__.py
galaxy/data/model/cmd.py
galaxy/data/model/company.py
galaxy/data/model/factory.py
galaxy/data/model/file.py
galaxy/data/model/finance.py
galaxy/data/model/infra.py
galaxy/data/model/institution.py
galaxy/data/model/iso.py
galaxy/data/model/model.py
galaxy/data/model/net.py
galaxy/data/model/prog.py
galaxy/data/model/time.py
galaxy/data/protobuf/__init__.py
galaxy/data/protobuf/cmd_pb2.py
galaxy/data/protobuf/institution_pb2.py
galaxy/data/protobuf/iso_pb2.py
galaxy/data/protobuf/net_pb2.py
galaxy/data/protobuf/time_pb2.py
galaxy/data/protobuf/uuid_pb2.py
galaxy/data/serial.py
galaxy_py_data-0.0.7.dist-info/AUTHORS
galaxy_py_data-0.0.7.dist-info/COPYING.md
galaxy_py_data-0.0.7.dist-info/LICENSE.txt
galaxy_py_data-0.0.7.dist-info/METADATA
galaxy_py_data-0.0.7.dist-info/WHEEL
galaxy_py_data-0.0.7.dist-info/RECORD
