Metadata-Version: 2.3
Name: galaxy-py-data
Version: 0.0.7
Summary: Python Data for the Galaxy Project
License: Apache-2.0
Keywords: galaxy,galaxy-data
Author: Bastien Saltel
Author-email: bastien.saltel@gmail.com
Maintainer: Bastien Saltel
Maintainer-email: bastien.saltel@gmail.com
Requires-Python: >=3.10
Classifier: Development Status :: 3 - Alpha
Classifier: Programming Language :: Python :: 3
Classifier: Operating System :: OS Independent
Requires-Dist: asyncpg
Requires-Dist: cryptography
Requires-Dist: django
Requires-Dist: galaxy-py-perfo
Requires-Dist: galaxy-py-service
Requires-Dist: galaxy-py-utils
Requires-Dist: influxalchemy
Requires-Dist: influxdb
Requires-Dist: msgpack
Requires-Dist: protobuf
Requires-Dist: psycopg
Requires-Dist: psycopg-binary
Requires-Dist: pygresql
Requires-Dist: snowflake-sqlalchemy
Requires-Dist: sqlalchemy
Requires-Dist: transitions
Project-URL: Changelog, https://github.com/bsaltel/galaxy-py-data/blob/main/CHANGELOG.md
Project-URL: Documentation, https://github.com/bsaltel/galaxy-py-data
Project-URL: Homepage, https://github.com/bsaltel/galaxy-py-data
Project-URL: Issues, https://github.com/bsaltel/galaxy-py-data/issues
Project-URL: Repository, https://github.com/bsaltel/galaxy-py-data.git
